chiapos.cpython-38-darwin.so
chiapos1-1.0.3.dev16.dist-info/LICENSE
chiapos1-1.0.3.dev16.dist-info/METADATA
chiapos1-1.0.3.dev16.dist-info/WHEEL
chiapos1-1.0.3.dev16.dist-info/top_level.txt
chiapos1-1.0.3.dev16.dist-info/RECORD
